NWUcellsr/__init__.py
NWUcellsr/craft_arch.py
NWUcellsr/sr.py
NWUcellsr/models/sr.pth
NWUcellsr-1.1.0.dist-info/METADATA
NWUcellsr-1.1.0.dist-info/WHEEL
NWUcellsr-1.1.0.dist-info/top_level.txt
NWUcellsr-1.1.0.dist-info/RECORD
