Metadata-Version: 2.1
Name: NWUcellsr
Version: 1.1.0
Summary: Your SDK description
Home-page: https://github.com/yourusername/yourrepo
Author: Your Name
Author-email: your.email@example.com
Keywords: your,keywords,here
Requires-Dist: addict
Requires-Dist: future
Requires-Dist: lmdb
Requires-Dist: numpy >=1.17
Requires-Dist: opencv-python
Requires-Dist: Pillow
Requires-Dist: pyyaml
Requires-Dist: requests
Requires-Dist: scikit-image
Requires-Dist: scipy
Requires-Dist: tb-nightly
Requires-Dist: torch >=1.7
Requires-Dist: torchvision
Requires-Dist: tqdm
Requires-Dist: yapf
Requires-Dist: wandb
Requires-Dist: einops
